z2m_log_parser/__init__.py
z2m_log_parser/z2m_log_parser.py
z2m_log_parser-0.1.1.dist-info/METADATA
z2m_log_parser-0.1.1.dist-info/WHEEL
z2m_log_parser-0.1.1.dist-info/licenses/LICENSE
z2m_log_parser-0.1.1.dist-info/RECORD
